src/awsideman/__init__.py
src/awsideman/aws_clients/__init__.py
src/awsideman/aws_clients/cached_client.py
src/awsideman/aws_clients/manager.py
src/awsideman/backup_restore/__init__.py
src/awsideman/backup_restore/audit.py
src/awsideman/backup_restore/backends.py
src/awsideman/backup_restore/backup_diff_manager.py
src/awsideman/backup_restore/backup_resolver.py
src/awsideman/backup_restore/collector.py
src/awsideman/backup_restore/comparators.py
src/awsideman/backup_restore/cross_account.py
src/awsideman/backup_restore/diff_engine.py
src/awsideman/backup_restore/diff_models.py
src/awsideman/backup_restore/encryption.py
src/awsideman/backup_restore/enhanced_backup_manager.py
src/awsideman/backup_restore/enhanced_restore_manager.py
src/awsideman/backup_restore/error_handling.py
src/awsideman/backup_restore/export_import.py
src/awsideman/backup_restore/interfaces.py
src/awsideman/backup_restore/local_metadata_index.py
src/awsideman/backup_restore/manager.py
src/awsideman/backup_restore/models.py
src/awsideman/backup_restore/monitoring.py
src/awsideman/backup_restore/output_formatter.py
src/awsideman/backup_restore/performance.py
src/awsideman/backup_restore/rbac.py
src/awsideman/backup_restore/restore_manager.py
src/awsideman/backup_restore/retention.py
src/awsideman/backup_restore/schedule_manager.py
src/awsideman/backup_restore/security.py
src/awsideman/backup_restore/serialization.py
src/awsideman/backup_restore/storage.py
src/awsideman/backup_restore/validation.py
src/awsideman/bulk/__init__.py
src/awsideman/bulk/batch.py
src/awsideman/bulk/intelligent_backoff.py
src/awsideman/bulk/multi_account_batch.py
src/awsideman/bulk/multi_account_errors.py
src/awsideman/bulk/multi_account_progress.py
src/awsideman/bulk/performance_optimizer.py
src/awsideman/bulk/preview.py
src/awsideman/bulk/processors.py
src/awsideman/bulk/reporting.py
src/awsideman/bulk/resolver.py
src/awsideman/cache/__init__.py
src/awsideman/cache/aws_client.py
src/awsideman/cache/backends/__init__.py
awsideman-0.1.2a0.dist-info/METADATA
awsideman-0.1.2a0.dist-info/WHEEL
awsideman-0.1.2a0.dist-info/entry_points.txt
awsideman-0.1.2a0.dist-info/RECORD
