Metadata-Version: 2.3
Name: awsideman
Version: 0.1.2a0
Summary: AWS Identity Center Manager - A CLI tool for managing AWS Identity Center operations
License: MIT
Keywords: aws,identity-center,iam,cli,management
Author: Erhan Vikyol
Requires-Python: >=3.9,<4.0
Classifier: Development Status :: 3 - Alpha
Classifier: Intended Audience :: System Administrators
Classifier: License :: OSI Approved :: MIT License
Classifier: Programming Language :: Python :: 3
Classifier: Programming Language :: Python :: 3.9
Classifier: Programming Language :: Python :: 3.10
Classifier: Programming Language :: Python :: 3.11
Classifier: Programming Language :: Python :: 3.12
Classifier: Programming Language :: Python :: 3.13
Classifier: Topic :: System :: Systems Administration
Classifier: Topic :: Utilities
Requires-Dist: aioboto3 (>=12.0.0,<13.0.0)
Requires-Dist: aiofiles (>=23.0.0,<24.0.0)
Requires-Dist: aiohttp (>=3.8.0,<4.0.0)
Requires-Dist: boto3 (>=1.28.0,<2.0.0)
Requires-Dist: click (<8.2.0)
Requires-Dist: cryptography (>=3.4.8,<45.0.0)
Requires-Dist: keyring (>=23.0.0,<25.0.0)
Requires-Dist: lz4 (>=4.4.4,<5.0.0)
Requires-Dist: psutil (>=7.0.0,<8.0.0)
Requires-Dist: pydantic (>=2.0.0,<3.0.0)
Requires-Dist: pyyaml (>=6.0,<7.0)
Requires-Dist: rich (>=13.4.2,<14.0.0)
Requires-Dist: typer (==0.7.0)
Project-URL: Homepage, https://floccus.se/awsideman
Project-URL: Repository, https://github.com/vikyol/awsideman
